mutstring.py
mutstring-1.0.1.dist-info/LICENSE
mutstring-1.0.1.dist-info/METADATA
mutstring-1.0.1.dist-info/WHEEL
mutstring-1.0.1.dist-info/top_level.txt
mutstring-1.0.1.dist-info/RECORD
