Metadata-Version: 2.1
Name: mutstring
Version: 1.0.1
Summary: please never use this
Author: ZeroIntensity
Author-email: <zintensitydev@gmail.com>
License: MIT
Keywords: python,strings,mutability
Classifier: Programming Language :: Python :: 3.6
Classifier: Programming Language :: Python :: 3.7
Classifier: Programming Language :: Python :: 3.8
Classifier: Programming Language :: Python :: 3.9
Classifier: Programming Language :: Python :: 3.10
Classifier: Programming Language :: Python :: 3.11
Classifier: Programming Language :: Python :: Implementation :: CPython
License-File: LICENSE
Requires-Dist: pointers.py
